
[
  {
    "modelId": "yamaha-mt-07",
    "modelName": "Yamaha MT-07",
    "brand": "Yamaha",
    "year": "2021+",
    "imageUrl": "https://images.unsplash.com/photo-1621699353928-09192b03a31c?q=80&w=2070&auto=format&fit=crop",
    "imageHint": "Yamaha MT-07",
    "engine": {
      "bridage": "✔ Permis A2 (bridable à 35 kW)",
      "type": "Bicylindre en ligne CP2, 4 temps, refroidissement liquide",
      "displacement": "689 cm³",
      "power": "54,0 kW (73,4 ch) à 8 750 tr/min",
      "torque": "67,0 N.m (6,8 m.kgf) à 6 500 tr/min",
      "alimentation": "Injection électronique"
    },
    "dimensions": {
      "seatHeight": "805 mm",
      "wetWeight": "184 kg",
      "fuelCapacity": "14 L",
      "wheelbase": "1 400 mm"
    },
    "chassis": {
      "frame": "Cadre type Diamant en acier",
      "frontSuspension": "Fourche télescopique, Ø 41 mm",
      "rearSuspension": "Mono-amortisseur réglable",
      "frontBrake": "Double disque, Ø 298 mm",
      "rearBrake": "Simple disque, Ø 245 mm",
      "frontTire": "120/70 ZR 17",
      "rearTire": "180/55 ZR 17"
    },
    "introduction": "La Yamaha MT-07 est la référence absolue du segment A2. Son moteur CP2 est réputé pour son couple et sa fiabilité exceptionnelle. Un entretien rigoureux est la clé pour conserver son agrément de conduite.",
    "content": [
      { "type": "heading", "text": "Préparez votre prochaine révision sans surprise." },
      { "type": "paragraph", "text": "Comparez les garages proches de chez vous pour votre Yamaha MT-07." },
      { "type": "cta-compare", "text": "🔘 Voir les garages autour de moi" },
      { "type": "heading", "text": "Intervalles d’entretien constructeur MT-07" },
      { "type": "table", "headers": ["Kilométrage", "Entretien à effectuer"], "rows": [
          ["1 000 km", "Révision de rodage (Forfait Eco)"],
          ["10 000 km", "Vidange + contrôles (Forfait Essentiel)"],
          ["20 000 km", "Bougies + Filtre air (Forfait Performance)"],
          ["40 000 km", "Réglage soupapes (Forfait Excellence)"]
      ]},
      { "type": "paragraph", "html": "👉 Une vidange annuelle reste recommandée même si le kilométrage n’est pas atteint." },
      { "type": "heading", "text": "Prix moyen des révisions (Forfaits Yamaha)" },
      { "type": "table", "headers": ["Révision", "Prix moyen constaté"], "rows": [
          ["1 000 km", "120 à 200 €"],
          ["10 000 km", "200 à 280 €"],
          ["20 000 km", "400 à 500 €"],
          ["40 000 km", "750 à 850 €"]
      ]},
      { "type": "paragraph", "html": "Les tarifs peuvent varier selon l’atelier et la région. Comparez les professionnels autour de vous avant de prendre rendez-vous." },
      { "type": "cta-compare", "text": "🔘 Comparer les ateliers près de moi" },
      { "type": "heading", "text": "Les consommables à surveiller" },
      { "type": "table", "headers": ["Pièce", "Durée moyenne"], "rows": [
        ["Pneus", "8 000 à 15 000 km"],
        ["Kit chaîne", "20 000 à 30 000 km"],
        ["Plaquettes", "10 000 à 20 000 km"],
        ["Batterie", "3 à 5 ans"]
      ]},
      { "type": "heading", "text": "Fiabilité et problèmes connus" },
      { "type": "list", "items": [
          "Finition des peintures de cadre (selon millésime)",
          "Batterie d’origine parfois juste par grand froid",
          "Tension de chaîne à surveiller régulièrement"
      ]},
      { "type": "cta-concession", "text": "🔘 Voir les Yamaha MT-07 en concession" },
      { "type": "heading", "text": "Conseils pour prolonger la durée de vie" },
      { "type": "list", "items": [
          "Temps de chauffe moteur impératif avant de monter dans les tours",
          "Graissage de la chaîne tous les 500 km ou après chaque pluie",
          "Vidange annuelle même si le kilométrage n'est pas atteint"
      ]},
      { "type": "heading", "text": "FAQ entretien MT-07" },
      { "type": "paragraph", "html": "<strong>Quand faire la vidange ?</strong><br/>Tous les 10 000 km ou tous les ans au premier des deux termes échus." },
      { "type": "paragraph", "html": "<strong>Le moteur CP2 est-il fiable ?</strong><br/>Oui, c'est l'un des moteurs les plus robustes et éprouvés du marché actuel." },
      { "type": "heading", "text": "Conclusion" },
      { "type": "paragraph", "text": "Simple et robuste, la MT-07 est extrêmement économique à l'usage si l'on respecte les préconisations du constructeur." },
      { "type": "signature", "text": "L'équipe Label Moto", "imageUrl": "/images/Stamp-LM.png?v=2", "alt": "Cachet Label Moto" }
    ]
  },
  {
    "modelId": "honda-cb500-hornet",
    "modelName": "Honda CB500F / CB500 Hornet",
    "brand": "Honda",
    "year": "2022+",
    "imageUrl": "https://images.unsplash.com/photo-1591637333184-19aa84b3e01f?q=80&w=2000&auto=format&fit=crop",
    "imageHint": "Honda CB500 Hornet",
    "engine": {
      "bridage": "✔ Permis A2 (moto A2 native – pas de bridage nécessaire)",
      "type": "Bicylindre en ligne, 4 temps, refroidissement liquide, DOHC 8 soupapes",
      "displacement": "471 cm³",
      "power": "35 kW (≈47,5 ch) à 8 500 tr/min",
      "torque": "43 N.m à 6 500 tr/min",
      "alimentation": "Injection électronique PGM-FI"
    },
    "dimensions": {
      "seatHeight": "785 mm",
      "wetWeight": "189 kg",
      "fuelCapacity": "17,1 L",
      "wheelbase": "1 410 mm"
    },
    "chassis": {
      "frame": "Cadre acier type diamant",
      "frontSuspension": "Fourche inversée Showa SFF-BP Ø41 mm",
      "rearSuspension": "Mono-amortisseur Pro-Link réglable",
      "frontBrake": "Double disque Ø296 mm",
      "rearBrake": "Disque Ø240 mm",
      "frontTire": "120/70 ZR17",
      "rearTire": "160/60 ZR17"
    },
    "introduction": "La Honda CB500F (aujourd’hui appelée CB500 Hornet) est l’une des motos les plus accessibles pour le permis A2. Son moteur bicylindre de 471 cm³ est réputé pour sa souplesse, sa fiabilité et son faible coût d’entretien.",
    "content": [
      { "type": "heading", "text": "Préparez votre prochaine révision sans surprise." },
      { "type": "paragraph", "text": "Comparez les garages proches de chez vous pour votre Honda CB500F." },
      { "type": "cta-compare", "text": "🔘 Voir les garages autour de moi" },
      { "type": "heading", "text": "Intervalles d’entretien constructeur CB500F" },
      { "type": "table", "headers": ["Kilométrage", "Entretien à effectuer"], "rows": [
          ["1 000 km", "Révision de rodage (Forfait Eco)"],
          ["12 000 km", "Vidange + contrôles (Forfait Essentiel)"],
          ["24 000 km", "Bougies + filtre air (Forfait Performance)"],
          ["48 000 km", "Réglage soupapes + entretien complet (Forfait Excellence)"]
      ]},
      { "type": "paragraph", "html": "👉 Une vidange annuelle reste recommandée même si le kilométrage n’est pas atteint." },
      { "type": "heading", "text": "Prix moyen des révisions (estimation)" },
      { "type": "table", "headers": ["Révision", "Prix moyen constaté"], "rows": [
          ["1 000 km", "120 à 180 €"],
          ["12 000 km", "200 à 280 €"],
          ["24 000 km", "350 à 450 €"],
          ["48 000 km", "600 à 800 €"]
      ]},
      { "type": "paragraph", "html": "Les tarifs peuvent varier selon l’atelier et la région. Comparez les professionnels autour de vous avant de prendre rendez-vous." },
      { "type": "cta-compare", "text": "🔘 Comparer les ateliers près de moi" },
      { "type": "heading", "text": "Les consommables à surveiller" },
      { "type": "table", "headers": ["Pièce", "Durée moyenne"], "rows": [
        ["Pneus", "10 000 à 18 000 km"],
        ["Kit chaîne", "20 000 à 30 000 km"],
        ["Plaquettes", "10 000 à 20 000 km"],
        ["Batterie", "3 à 5 ans"]
      ]},
      { "type": "heading", "text": "Fiabilité et problèmes connus" },
      { "type": "list", "items": [
          "Suspensions parfois jugées souples en conduite sportive",
          "Peinture du cadre sensible aux projections",
          "Chaîne d’origine à surveiller régulièrement"
      ]},
      { "type": "cta-concession", "text": "🔘 Voir les Honda CB500F en concession" },
      { "type": "heading", "text": "Conseils pour prolonger la durée de vie" },
      { "type": "list", "items": [
          "Respecter les intervalles d’entretien constructeur",
          "Graisser la chaîne régulièrement",
          "Vérifier la pression des pneus",
          "Laisser chauffer le moteur avant de rouler"
      ]},
      { "type": "heading", "text": "FAQ entretien CB500F" },
      { "type": "paragraph", "html": "<strong>Quand faire la vidange ?</strong><br/>Tous les 12 000 km ou une fois par an." },
      { "type": "paragraph", "html": "<strong>La CB500F est-elle fiable ?</strong><br/>Oui, le moteur bicylindre Honda de 471 cm³ est réputé pour sa robustesse et sa longévité." },
      { "type": "heading", "text": "Conclusion" },
      { "type": "paragraph", "text": "La Honda CB500F / Hornet 500 est une moto simple, fiable et économique, parfaitement adaptée aux jeunes permis A2. Avec un entretien régulier, elle reste l’une des motos les plus accessibles et durables de sa catégorie." },
      { "type": "signature", "text": "L'équipe Label Moto", "imageUrl": "/images/Stamp-LM.png?v=2", "alt": "Cachet Label Moto" }
    ]
  },
  {
    "modelId": "honda-nx500",
    "modelName": "Honda NX500 / CB500X",
    "brand": "Honda",
    "year": "2024+",
    "imageUrl": "https://images.unsplash.com/photo-1568772585407-9361f9bf3a87?q=80&w=2070&auto=format&fit=crop",
    "imageHint": "Honda NX500",
    "engine": {
      "bridage": "✔ Permis A2 (moto A2 native – pas de bridage nécessaire)",
      "type": "Bicylindre en ligne, 4 temps, refroidissement liquide, DOHC 8 soupapes",
      "displacement": "471 cm³",
      "power": "35 kW (47,5 ch) à 8 600 tr/min",
      "torque": "43 N.m à 6 500 tr/min",
      "alimentation": "Injection électronique PGM-FI"
    },
    "dimensions": {
      "seatHeight": "830 mm",
      "wetWeight": "≈196 kg",
      "fuelCapacity": "17,5 L",
      "wheelbase": "1 445 mm"
    },
    "chassis": {
      "frame": "Cadre acier type diamant",
      "frontSuspension": "Fourche inversée Showa SFF-BP Ø41 mm",
      "rearSuspension": "Mono-amortisseur Pro-Link",
      "frontBrake": "Double disque Ø296 mm",
      "rearBrake": "Disque Ø240 mm",
      "frontTire": "110/80 R19",
      "rearTire": "160/60 R17"
    },
    "introduction": "La Honda NX500 (anciennement CB500X) est l’un des trails A2 les plus polyvalents du marché. Elle combine confort, autonomie et fiabilité. Son moteur bicylindre de 471 cm³ est réputé robuste et demande un entretien relativement simple.",
    "content": [
      { "type": "heading", "text": "Préparez votre prochaine révision sans surprise." },
      { "type": "paragraph", "text": "Comparez les garages proches de chez vous pour votre Honda NX500." },
      { "type": "cta-compare", "text": "🔘 Voir les garages autour de moi" },
      { "type": "heading", "text": "Intervalles d’entretien constructeur NX500" },
      { "type": "table", "headers": ["Kilométrage", "Entretien à effectuer"], "rows": [
          ["1 000 km", "Révision de rodage (Forfait Eco)"],
          ["12 000 km", "Vidange + contrôles (Forfait Essentiel)"],
          ["24 000 km", "Bougies + filtre air (Forfait Performance)"],
          ["48 000 km", "Réglage soupapes (Forfait Excellence)"]
      ]},
      { "type": "paragraph", "html": "👉 Une vidange annuelle reste recommandée même si le kilométrage n’est pas atteint." },
      { "type": "heading", "text": "Prix moyen des révisions (estimation)" },
      { "type": "table", "headers": ["Révision", "Prix moyen constaté"], "rows": [
          ["1 000 km", "120 à 180 €"],
          ["12 000 km", "200 à 280 €"],
          ["24 000 km", "350 à 450 €"],
          ["48 000 km", "600 à 800 €"]
      ]},
      { "type": "paragraph", "html": "Les tarifs peuvent varier selon l’atelier et la région. Comparez les professionnels autour de vous avant de prendre rendez-vous." },
      { "type": "cta-compare", "text": "🔘 Comparer les ateliers près de moi" },
      { "type": "heading", "text": "Les consommables à surveiller" },
      { "type": "table", "headers": ["Pièce", "Durée moyenne"], "rows": [
        ["Pneus", "10 000 à 18 000 km"],
        ["Kit chaîne", "20 000 à 30 000 km"],
        ["Plaquettes", "10 000 à 20 000 km"],
        ["Batterie", "3 à 5 ans"]
      ]},
      { "type": "heading", "text": "Fiabilité et problèmes connus" },
      { "type": "list", "items": [
          "Suspensions parfois souples en conduite sportive",
          "Protection au vent limitée avec la bulle d’origine",
          "Chaîne d’origine à surveiller régulièrement"
      ]},
      { "type": "cta-concession", "text": "🔘 Voir les Honda NX500 en concession" },
      { "type": "heading", "text": "Conseils pour prolonger la durée de vie" },
      { "type": "list", "items": [
          "Respecter les intervalles d’entretien constructeur",
          "Graisser régulièrement la chaîne",
          "Vérifier la pression des pneus avant les longs trajets",
          "Vidange annuelle recommandée"
      ]},
      { "type": "heading", "text": "FAQ entretien NX500" },
      { "type": "paragraph", "html": "<strong>Quand faire la vidange ?</strong><br/>Tous les 12 000 km ou une fois par an." },
      { "type": "paragraph", "html": "<strong>La NX500 est-elle adaptée au permis A2 ?</strong><br/>Oui, sa puissance de 47,5 ch correspond parfaitement à la limite du permis A2." },
      { "type": "heading", "text": "Conclusion" },
      { "type": "paragraph", "text": "Polyvalente et fiable, la Honda NX500 / CB500X est l’un des meilleurs trails accessibles aux permis A2. Avec un entretien régulier, ce moteur Honda peut parcourir de très nombreux kilomètres tout en restant économique à l’usage." },
      { "type": "signature", "text": "L'équipe Label Moto", "imageUrl": "/images/Stamp-LM.png?v=2", "alt": "Cachet Label Moto" }
    ]
  },
  {
    "modelId": "honda-cbr500r",
    "modelName": "Honda CBR500R",
    "brand": "Honda",
    "year": "2022+",
    "imageUrl": "https://images.unsplash.com/photo-1568772585407-9361f9bf3a87?q=80&w=2070&auto=format&fit=crop",
    "imageHint": "Honda CBR500R",
    "engine": {
      "bridage": "✔ Permis A2 (moto A2 native – pas de bridage nécessaire)",
      "type": "Bicylindre en ligne, 4 temps, refroidissement liquide, double ACT, 8 soupapes",
      "displacement": "471 cm³",
      "power": "35 kW (47,5 ch) à 8 600 tr/min",
      "torque": "43 N.m à 6 500 tr/min",
      "alimentation": "Injection électronique PGM-FI"
    },
    "dimensions": {
      "seatHeight": "785 mm",
      "wetWeight": "≈ 192 kg",
      "fuelCapacity": "17,1 L",
      "wheelbase": "1 410 mm"
    },
    "chassis": {
      "frame": "Cadre acier type diamant",
      "frontSuspension": "Fourche inversée Showa SFF-BP Ø41 mm",
      "rearSuspension": "Mono-amortisseur Pro-Link",
      "frontBrake": "Double disque Ø296 mm",
      "rearBrake": "Disque Ø240 mm",
      "frontTire": "120/70 ZR17",
      "rearTire": "160/60 ZR17"
    },
    "introduction": "La Honda CBR500R est l’une des sportives A2 les plus accessibles du marché. Son moteur bicylindre de 471 cm³ est réputé pour sa souplesse, sa sobriété et sa très bonne fiabilité. Un entretien suivi permet de conserver ses performances et d’éviter les réparations coûteuses.",
    "content": [
      { "type": "heading", "text": "Préparez votre prochaine révision sans surprise." },
      { "type": "paragraph", "text": "Comparez les garages proches de chez vous pour votre Honda CBR500R." },
      { "type": "cta-compare", "text": "🔘 Voir les garages autour de moi" },
      { "type": "heading", "text": "Intervalles d’entretien constructeur CBR500R" },
      { "type": "table", "headers": ["Kilométrage", "Entretien à effectuer"], "rows": [
          ["1 000 km", "Révision de rodage"],
          ["12 000 km", "Vidange + contrôles"],
          ["24 000 km", "Bougies + filtre à air"],
          ["48 000 km", "Réglage soupapes + entretien complet"]
      ]},
      { "type": "paragraph", "html": "👉 Une vidange annuelle reste recommandée même si le kilométrage n’est pas atteint." },
      { "type": "heading", "text": "Prix moyen des révisions" },
      { "type": "table", "headers": ["Révision", "Prix moyen constaté"], "rows": [
          ["1 000 km", "120 à 180 €"],
          ["12 000 km", "200 à 280 €"],
          ["24 000 km", "350 à 450 €"],
          ["48 000 km", "600 à 800 €"]
      ]},
      { "type": "paragraph", "html": "Les tarifs peuvent varier selon l’atelier et la région. Comparez les professionnels autour de vous avant de prendre rendez-vous." },
      { "type": "cta-compare", "text": "🔘 Comparer les ateliers près de moi" },
      { "type": "heading", "text": "Les consommables à surveiller" },
      { "type": "table", "headers": ["Pièce", "Durée moyenne"], "rows": [
        ["Pneus", "10 000 à 15 000 km"],
        ["Kit chaîne", "20 000 à 30 000 km"],
        ["Plaquettes", "10 000 à 20 000 km"],
        ["Batterie", "3 à 5 ans"]
      ]},
      { "type": "heading", "text": "Fiabilité et problèmes connus" },
      { "type": "list", "items": [
          "Suspensions parfois jugées souples en conduite sportive",
          "Chaîne d’origine à surveiller régulièrement",
          "Batterie parfois un peu juste après immobilisation prolongée"
      ]},
      { "type": "cta-concession", "text": "🔘 Voir les Honda CBR500R en concession" },
      { "type": "heading", "text": "Conseils pour prolonger la durée de vie" },
      { "type": "list", "items": [
          "Temps de chauffe moteur recommandé avant de monter dans les tours",
          "Graissage de la chaîne tous les 500 km ou après chaque pluie",
          "Vidange annuelle même si le kilométrage n’est pas atteint"
      ]},
      { "type": "heading", "text": "FAQ entretien CBR500R" },
      { "type": "paragraph", "html": "<strong>Quand faire la vidange ?</strong><br/>Tous les 12 000 km ou tous les ans au premier des deux termes échus." },
      { "type": "paragraph", "html": "<strong>La Honda CBR500R est-elle fiable ?</strong><br/>Oui, son moteur bicylindre 471 cm³ fait partie des mécaniques Honda les plus éprouvées en permis A2." },
      { "type": "heading", "text": "Conclusion" },
      { "type": "paragraph", "text": "Accessible, sobre et robuste, la Honda CBR500R est l’une des sportives A2 les plus économiques à l’usage. Si l’on respecte les préconisations constructeur, son entretien reste simple et raisonnable." },
      { "type": "signature", "text": "L'équipe Label Moto", "imageUrl": "/images/Stamp-LM.png?v=2", "alt": "Cachet Label Moto" }
    ]
  },
  {
    "modelId": "honda-xl750-transalp",
    "modelName": "Honda XL750 Transalp",
    "brand": "Honda",
    "year": "2023+",
    "imageUrl": "https://images.unsplash.com/photo-1558981403-c5f9899a28bc?q=80&w=2070&auto=format&fit=crop",
    "imageHint": "Honda XL750 Transalp",
    "engine": {
      "bridage": "✔ Permis A2 (bridable à 35 kW)",
      "type": "Bicylindre en ligne, 4 temps, refroidissement liquide, Unicam, 8 soupapes",
      "displacement": "755 cm³",
      "power": "67,5 kW (92 ch) à 9 500 tr/min",
      "torque": "75 N.m à 7 250 tr/min",
      "alimentation": "Injection électronique PGM-FI"
    },
    "dimensions": {
      "seatHeight": "850 mm",
      "wetWeight": "210 kg",
      "fuelCapacity": "16,9 L",
      "wheelbase": "1 560 mm"
    },
    "chassis": {
      "frame": "Cadre acier type diamant",
      "frontSuspension": "Fourche inversée Showa SFF-CA Ø43 mm",
      "rearSuspension": "Mono-amortisseur Pro-Link",
      "frontBrake": "Double disque Ø310 mm, étriers 2 pistons",
      "rearBrake": "Disque Ø256 mm",
      "frontTire": "90/90 R21",
      "rearTire": "150/70 R18"
    },
    "introduction": "La Honda XL750 Transalp est un trail polyvalent très apprécié pour le voyage comme pour un usage quotidien. Son bicylindre de 755 cm³ offre un excellent compromis entre performances, sobriété et agrément. Un entretien régulier permet de préserver sa fiabilité et d’éviter les grosses factures sur le long terme.",
    "content": [
      { "type": "heading", "text": "Préparez votre prochaine révision sans surprise." },
      { "type": "paragraph", "text": "Comparez les garages proches de chez vous pour votre Honda XL750 Transalp." },
      { "type": "cta-compare", "text": "🔘 Voir les garages autour de moi" },
      { "type": "heading", "text": "Intervalles d’entretien constructeur XL750 Transalp" },
      { "type": "table", "headers": ["Kilométrage", "Entretien à effectuer"], "rows": [
          ["1 000 km", "Révision de rodage"],
          ["12 000 km", "Vidange + contrôles"],
          ["24 000 km", "Bougies + filtre à air"],
          ["48 000 km", "Réglage soupapes + entretien complet"]
      ]},
      { "type": "paragraph", "html": "👉 Une vidange annuelle reste recommandée même si le kilométrage n’est pas atteint." },
      { "type": "heading", "text": "Prix moyen des révisions (estimation)" },
      { "type": "table", "headers": ["Révision", "Prix moyen constaté"], "rows": [
          ["1 000 km", "150 à 220 €"],
          ["12 000 km", "220 à 320 €"],
          ["24 000 km", "400 à 550 €"],
          ["48 000 km", "700 à 900 €"]
      ]},
      { "type": "paragraph", "html": "Les tarifs peuvent varier selon l’atelier, la région et les opérations complémentaires. Il s’agit d’une <strong>estimation réaliste</strong> pour se prémunir d’éventuelles évolutions tarifaires." },
      { "type": "cta-compare", "text": "🔘 Comparer les ateliers près de moi" },
      { "type": "heading", "text": "Les consommables à surveiller" },
      { "type": "table", "headers": ["Pièce", "Durée moyenne"], "rows": [
        ["Pneus", "8 000 à 15 000 km"],
        ["Kit chaîne", "20 000 à 30 000 km"],
        ["Plaquettes", "10 000 à 20 000 km"],
        ["Batterie", "3 à 5 ans"]
      ]},
      { "type": "heading", "text": "Fiabilité et problèmes connus" },
      { "type": "list", "items": [
          "Chaleur moteur perceptible en ville l’été",
          "Bulle d’origine parfois jugée un peu juste pour les grands trajets",
          "Chaîne d’origine à surveiller régulièrement",
          "Suspensions d’origine orientées confort plus que conduite très sportive"
      ]},
      { "type": "cta-concession", "text": "🔘 Voir les Honda XL750 Transalp en concession" },
      { "type": "heading", "text": "Conseils pour prolonger la durée de vie" },
      { "type": "list", "items": [
          "Respecter les intervalles d’entretien constructeur",
          "Graisser la chaîne régulièrement, surtout après roulage sous la pluie",
          "Vérifier la pression des pneus avant les longs trajets",
          "Vidange annuelle recommandée même en faible kilométrage"
      ]},
      { "type": "heading", "text": "FAQ entretien XL750 Transalp" },
      { "type": "paragraph", "html": "<strong>Quand faire la vidange ?</strong><br/>Tous les 12 000 km ou tous les ans au premier des deux termes échus." },
      { "type": "paragraph", "html": "<strong>La Honda XL750 Transalp est-elle compatible A2 ?</strong><br/>Oui, Honda la propose en version <strong>A2 permis</strong>, avec bridage à 35 kW." },
      { "type": "heading", "text": "Conclusion" },
      { "type": "paragraph", "text": "Polyvalente, confortable et bien pensée pour le voyage, la Honda XL750 Transalp est un trail moderne très cohérent. Bien entretenue, elle reste raisonnable à l’usage et constitue une excellente option pour les motards qui veulent une vraie moto de route et d’aventure." },
      { "type": "signature", "text": "L'équipe Label Moto", "imageUrl": "/images/Stamp-LM.png?v=3", "alt": "Cachet Label Moto" }
    ]
  },
  {
    "modelId": "yamaha-r7",
    "modelName": "Yamaha R7",
    "brand": "Yamaha",
    "year": "2022+",
    "imageUrl": "https://images.unsplash.com/photo-1621699353928-09192b03a31c?q=80&w=2070&auto=format&fit=crop",
    "imageHint": "Yamaha R7",
    "engine": {
      "bridage": "✔ Permis A2 (bridable à 35 kW)",
      "type": "Bicylindre en ligne CP2, 4 temps, refroidissement liquide, DOHC",
      "displacement": "689 cm³",
      "power": "54,0 kW (73,4 ch) à 8 750 tr/min",
      "torque": "67 N.m à 6 500 tr/min",
      "alimentation": "Injection électronique"
    },
    "dimensions": {
      "seatHeight": "835 mm",
      "wetWeight": "188 kg",
      "fuelCapacity": "13 L",
      "wheelbase": "1 395 mm"
    },
    "chassis": {
      "frame": "Cadre acier type diamant",
      "frontSuspension": "Fourche inversée KYB Ø41 mm, entièrement réglable",
      "rearSuspension": "Bras oscillant avec mono-amortisseur KYB",
      "frontBrake": "Double disque Ø298 mm, étriers radiaux 4 pistons",
      "rearBrake": "Disque Ø245 mm",
      "frontTire": "120/70 ZR17",
      "rearTire": "180/55 ZR17"
    },
    "introduction": "La Yamaha R7 est une sportive accessible basée sur la plateforme MT-07. Elle utilise le moteur CP2 réputé pour son couple et sa fiabilité. Même si elle est conçue pour une utilisation sportive, un entretien régulier permet de conserver ses performances.",
    "content": [
      { "type": "heading", "text": "Préparez votre prochaine révision sans surprise." },
      { "type": "paragraph", "text": "Comparez les garages proches de chez vous pour votre Yamaha R7." },
      { "type": "cta-compare", "text": "🔘 Voir les garages autour de moi" },
      { "type": "heading", "text": "Intervalles d’entretien constructeur R7" },
      { "type": "table", "headers": ["Kilométrage", "Entretien à effectuer"], "rows": [
          ["1 000 km", "Révision de rodage (Forfait Eco)"],
          ["10 000 km", "Vidange + contrôles (Forfait Essentiel)"],
          ["20 000 km", "Bougies + filtre air (Forfait Performance)"],
          ["40 000 km", "Réglage soupapes (Forfait Excellence)"]
      ]},
      { "type": "paragraph", "html": "👉 Une vidange annuelle reste recommandée même si le kilométrage n’est pas atteint." },
      { "type": "heading", "text": "Prix moyen des révisions (Forfaits Yamaha)" },
      { "type": "table", "headers": ["Révision", "Prix moyen constaté"], "rows": [
          ["1 000 km", "140 à 220 €"],
          ["10 000 km", "180 à 260 €"],
          ["20 000 km", "320 à 460 €"],
          ["40 000 km", "580 à 720 €"]
      ]},
      { "type": "paragraph", "html": "Les tarifs peuvent varier selon l’atelier et la région. Comparez les professionnels autour de vous avant de prendre rendez-vous." },
      { "type": "cta-compare", "text": "🔘 Comparer les ateliers près de moi" },
      { "type": "heading", "text": "Les consommables à surveiller" },
      { "type": "table", "headers": ["Pièce", "Durée moyenne"], "rows": [
        ["Pneus", "6 000 à 10 000 km"],
        ["Kit chaîne", "20 000 à 30 000 km"],
        ["Plaquettes", "8 000 à 15 000 km"],
        ["Batterie", "3 à 5 ans"]
      ]},
      { "type": "heading", "text": "Fiabilité et problèmes connus" },
      { "type": "list", "items": [
          "Suspensions fermes pour usage routier",
          "Position de conduite fatigante sur longs trajets",
          "Chaîne d’origine à surveiller régulièrement"
      ]},
      { "type": "cta-concession", "text": "🔘 Voir les Yamaha R7 en concession" },
      { "type": "heading", "text": "Conseils pour prolonger la durée de vie" },
      { "type": "list", "items": [
          "Temps de chauffe moteur avant conduite sportive",
          "Graissage chaîne régulier",
          "Vidange annuelle recommandée",
          "Contrôle fréquent de la pression des pneus"
      ]},
      { "type": "heading", "text": "FAQ entretien R7" },
      { "type": "paragraph", "html": "<strong>Quand faire la vidange ?</strong><br/>Tous les 10 000 km ou une fois par an." },
      { "type": "paragraph", "html": "<strong>La Yamaha R7 est-elle compatible A2 ?</strong><br/>Oui, elle peut être bridée à 35 kW pour le permis A2." },
      { "type": "heading", "text": "Conclusion" },
      { "type": "paragraph", "text": "Sportive et accessible, la Yamaha R7 combine performances et fiabilité grâce à son moteur CP2. Bien entretenue, elle reste relativement économique à l’usage pour une moto de cette catégorie." },
      { "type": "signature", "text": "L'équipe Label Moto", "imageUrl": "/images/Stamp-LM.png?v=2", "alt": "Cachet Label Moto" }
    ]
  },
  {
    "modelId": "yamaha-xsr700",
    "modelName": "Yamaha XSR700",
    "brand": "Yamaha",
    "year": "2021+",
    "imageUrl": "https://images.unsplash.com/photo-1558981403-c5f9899a28bc?q=80&w=2070&auto=format&fit=crop",
    "imageHint": "Yamaha XSR700",
    "engine": {
      "bridage": "✔ Permis A2 (bridable à 35 kW)",
      "type": "Bicylindre en ligne CP2, 4 temps, refroidissement liquide, DOHC",
      "displacement": "689 cm³",
      "power": "54 kW (73,4 ch) à 8 750 tr/min",
      "torque": "67 N.m à 6 500 tr/min",
      "alimentation": "Injection électronique"
    },
    "dimensions": {
      "seatHeight": "835 mm",
      "wetWeight": "188 kg",
      "fuelCapacity": "14 L",
      "wheelbase": "1 405 mm"
    },
    "chassis": {
      "frame": "Cadre acier type diamant",
      "frontSuspension": "Fourche télescopique Ø41 mm",
      "rearSuspension": "Bras oscillant avec mono-amortisseur",
      "frontBrake": "Double disque Ø282 mm",
      "rearBrake": "Disque Ø245 mm",
      "frontTire": "120/70 ZR17",
      "rearTire": "180/55 ZR17"
    },
    "introduction": "La Yamaha XSR700 est un roadster néo-rétro basé sur la plateforme MT-07. Son moteur CP2 combine couple, fiabilité et simplicité mécanique. Un entretien régulier permet de préserver ses performances et sa longévité.",
    "content": [
      { "type": "heading", "text": "Préparez votre prochaine révision sans surprise." },
      { "type": "paragraph", "text": "Comparez les garages proches de chez vous pour votre Yamaha XSR700." },
      { "type": "cta-compare", "text": "🔘 Voir les garages autour de moi" },
      { "type": "heading", "text": "Intervalles d’entretien constructeur XSR700" },
      { "type": "table", "headers": ["Kilométrage", "Entretien à effectuer"], "rows": [
          ["1 000 km", "Révision de rodage (Forfait Eco)"],
          ["10 000 km", "Vidange + contrôles (Forfait Essentiel)"],
          ["20 000 km", "Bougies + filtre air (Forfait Performance)"],
          ["40 000 km", "Réglage soupapes (Forfait Excellence)"]
      ]},
      { "type": "paragraph", "html": "👉 Une vidange annuelle reste recommandée." },
      { "type": "heading", "text": "Prix moyen des révisions (Forfaits Yamaha)" },
      { "type": "table", "headers": ["Révision", "Prix moyen constaté"], "rows": [
          ["1 000 km", "140 à 220 €"],
          ["10 000 km", "180 à 260 €"],
          ["20 000 km", "320 à 460 €"],
          ["40 000 km", "580 à 720 €"]
      ]},
      { "type": "paragraph", "html": "Les tarifs peuvent varier selon l’atelier et la région. Comparez les professionnels autour de vous avant de prendre rendez-vous." },
      { "type": "cta-compare", "text": "🔘 Comparer les ateliers près de moi" },
      { "type": "heading", "text": "Les consommables à surveiller" },
      { "type": "table", "headers": ["Pièce", "Durée moyenne"], "rows": [
        ["Pneus", "8 000 à 15 000 km"],
        ["Kit chaîne", "20 000 à 30 000 km"],
        ["Plaquettes", "10 000 à 20 000 km"],
        ["Batterie", "3 à 5 ans"]
      ]},
      { "type": "heading", "text": "Fiabilité et problèmes connus" },
      { "type": "list", "items": [
          "Suspensions d’origine assez souples",
          "Affichage compteur parfois difficile au soleil",
          "Chaîne d’origine à surveiller régulièrement"
      ]},
      { "type": "cta-concession", "text": "🔘 Voir les Yamaha XSR700 en concession" },
      { "type": "heading", "text": "Conseils pour prolonger la durée de vie" },
      { "type": "list", "items": [
          "Temps de chauffe moteur recommandé",
          "Graissage chaîne régulier",
          "Contrôle pression pneus fréquent",
          "Vidange annuelle conseillée"
      ]},
      { "type": "heading", "text": "FAQ entretien XSR700" },
      { "type": "paragraph", "html": "<strong>Quand faire la vidange ?</strong><br/>Tous les 10 000 km ou tous les ans." },
      { "type": "paragraph", "html": "<strong>Le moteur CP2 est-il fiable ?</strong><br/>Oui, c’est un moteur Yamaha très éprouvé utilisé sur plusieurs modèles." },
      { "type": "heading", "text": "Conclusion" },
      { "type": "paragraph", "text": "La Yamaha XSR700 combine style rétro, moteur coupleux et entretien raisonnable. Bien suivie, elle reste l’une des motos les plus agréables et économiques de la catégorie néo-rétro." },
      { "type": "signature", "text": "L'équipe Label Moto", "imageUrl": "/images/Stamp-LM.png?v=2", "alt": "Cachet Label Moto" }
    ]
  },
  {
    "modelId": "yamaha-mt-03",
    "modelName": "Yamaha MT-03",
    "brand": "Yamaha",
    "year": "2020+",
    "imageUrl": "https://images.unsplash.com/photo-1558981403-c5f9899a28bc?q=80&w=2070&auto=format&fit=crop",
    "imageHint": "Yamaha MT-03",
    "engine": {
      "bridage": "✔ Permis A2 (moto A2 native – pas de bridage nécessaire)",
      "type": "Bicylindre en ligne, 4 temps, refroidissement liquide, DOHC 4 soupapes",
      "displacement": "321 cm³",
      "power": "30,9 kW (≈42 ch) à 10 750 tr/min",
      "torque": "29,6 N.m à 9 000 tr/min",
      "alimentation": "Injection électronique"
    },
    "dimensions": {
      "seatHeight": "780 mm",
      "wetWeight": "168 kg",
      "fuelCapacity": "14 L",
      "wheelbase": "1 380 mm"
    },
    "chassis": {
      "frame": "Cadre diamant en acier",
      "frontSuspension": "Fourche inversée KYB Ø37 mm",
      "rearSuspension": "Mono-amortisseur avec bras oscillant",
      "frontBrake": "Disque Ø298 mm, étrier 2 pistons",
      "rearBrake": "Disque Ø220 mm",
      "frontTire": "110/70 R17",
      "rearTire": "140/70 R17"
    },
    "introduction": "La Yamaha MT-03 est l’un des roadsters les plus accessibles du marché. Légère, économique et facile à prendre en main, elle est très populaire auprès des jeunes permis. Son moteur bicylindre de 321 cm³ est réputé fiable.",
    "content": [
      { "type": "heading", "text": "Préparez votre prochaine révision sans surprise." },
      { "type": "paragraph", "text": "Comparez les garages proches de chez vous pour votre Yamaha MT-03." },
      { "type": "cta-compare", "text": "🔘 Voir les garages autour de moi" },
      { "type": "heading", "text": "Intervalles d’entretien constructeur MT-03" },
      { "type": "table", "headers": ["Kilométrage", "Entretien à effectuer"], "rows": [
          ["1 000 km", "Révision de rodage (Forfait Eco)"],
          ["10 000 km", "Vidange + contrôles (Forfait Essentiel)"],
          ["20 000 km", "Bougies + filtre air (Forfait Performance)"],
          ["40 000 km", "Contrôle soupapes (Forfait Excellence)"]
      ]},
      { "type": "paragraph", "html": "👉 Une vidange annuelle reste recommandée même si le kilométrage n’est pas atteint." },
      { "type": "heading", "text": "Prix moyen des révisions (estimation)" },
      { "type": "table", "headers": ["Révision", "Prix moyen constaté"], "rows": [
          ["1 000 km", "120 à 180 €"],
          ["10 000 km", "180 à 250 €"],
          ["20 000 km", "250 à 350 €"],
          ["40 000 km", "400 à 600 €"]
      ]},
      { "type": "paragraph", "html": "Les tarifs peuvent varier selon l’atelier et la région. Comparez les professionnels autour de vous avant de prendre rendez-vous." },
      { "type": "cta-compare", "text": "🔘 Comparer les ateliers près de moi" },
      { "type": "heading", "text": "Les consommables à surveiller" },
      { "type": "table", "headers": ["Pièce", "Durée moyenne"], "rows": [
        ["Pneus", "10 000 à 18 000 km"],
        ["Kit chaîne", "20 000 à 30 000 km"],
        ["Plaquettes", "10 000 à 20 000 km"],
        ["Batterie", "3 à 5 ans"]
      ]},
      { "type": "heading", "text": "Fiabilité et problèmes connus" },
      { "type": "list", "items": [
          "Suspension arrière parfois souples",
          "Manque de protection au vent sur voie rapide",
          "Chaîne d’origine à surveiller régulièrement"
      ]},
      { "type": "cta-concession", "text": "🔘 Voir les Yamaha MT-03 en concession" },
      { "type": "heading", "text": "Conseils pour prolonger la durée de vie" },
      { "type": "list", "items": [
          "Respecter les intervalles de vidange",
          "Graisser la chaîne régulièrement",
          "Vérifier souvent la pression des pneus",
          "Laisser chauffer le moteur avant de rouler"
      ]},
      { "type": "heading", "text": "FAQ entretien MT-03" },
      { "type": "paragraph", "html": "<strong>Quand faire la vidange ?</strong><br/>Tous les 10 000 km ou une fois par an." },
      { "type": "paragraph", "html": "<strong>La MT-03 est-elle adaptée aux débutants ?</strong><br/>Oui, sa puissance de 42 ch et son poids léger en font une excellente première moto." },
      { "type": "heading", "text": "Conclusion" },
      { "type": "paragraph", "text": "Accessible et économique, la Yamaha MT-03 est une moto idéale pour débuter ou pour un usage quotidien. Avec un entretien régulier, son moteur bicylindre peut parcourir de très nombreux kilomètres sans problème majeur." },
      { "type": "signature", "text": "L'équipe Label Moto", "imageUrl": "/images/Stamp-LM.png?v=2", "alt": "Cachet Label Moto" }
    ]
  }
]
